pipestat/__init__.py
pipestat/__main__.py
pipestat/_version.py
pipestat/argparser.py
pipestat/cli.py
pipestat/const.py
pipestat/exceptions.py
pipestat/helpers.py
pipestat/parsed_schema.py
pipestat/pipestat.py
pipestat/reports.py
pipestat/backends/__init__.py
pipestat/backends/abstract.py
pipestat/backends/db_backend/__init__.py
pipestat/backends/db_backend/db_helpers.py
pipestat/backends/db_backend/db_parsed_schema.py
pipestat/backends/db_backend/dbbackend.py
pipestat/backends/file_backend/__init__.py
pipestat/backends/file_backend/filebackend.py
pipestat/backends/pephub_backend/__init__.py
pipestat/backends/pephub_backend/pephubbackend.py
pipestat/jinja_templates/footer.html
pipestat/jinja_templates/footer_index.html
pipestat/jinja_templates/glossary.html
pipestat/jinja_templates/glossary_table.html
pipestat/jinja_templates/head.html
pipestat/jinja_templates/index.html
pipestat/jinja_templates/logo.html
pipestat/jinja_templates/navbar.html
pipestat/jinja_templates/navbar_links.html
pipestat/jinja_templates/navbar_list_parent.html
pipestat/jinja_templates/object.html
pipestat/jinja_templates/project_object.html
pipestat/jinja_templates/sample.html
pipestat/jinja_templates/status.html
pipestat/jinja_templates/status_table.html
pipestat/jinja_templates/status_table_no_links.html
pipestat/pipestatreader/README.md
pipestat/pipestatreader/__init__.py
pipestat/pipestatreader/reader.py
pipestat/schemas/pipestat_config_schema.yaml
pipestat/schemas/status_schema.yaml
pipestat/schemas/status_table_schema.yaml
pipestat-0.12.0.dist-info/LICENSE
pipestat-0.12.0.dist-info/METADATA
pipestat-0.12.0.dist-info/WHEEL
pipestat-0.12.0.dist-info/entry_points.txt
pipestat-0.12.0.dist-info/top_level.txt
pipestat-0.12.0.dist-info/RECORD
