Metadata-Version: 2.2
Name: pipestat
Version: 0.12.0
Summary: A pipeline results reporter
Home-page: https://github.com/pepkit/pipestat
Author: Michal Stolarczyk, Nathan Sheffield
License: BSD2
Keywords: project,metadata,bioinformatics,sequencing,ngs,workflow
Classifier: Development Status :: 4 - Beta
Classifier: License :: OSI Approved :: BSD License
Classifier: Programming Language :: Python :: 3.8
Classifier: Programming Language :: Python :: 3.9
Classifier: Programming Language :: Python :: 3.10
Classifier: Programming Language :: Python :: 3.11
Classifier: Topic :: Scientific/Engineering :: Bio-Informatics
License-File: LICENSE
Requires-Dist: jsonschema
Requires-Dist: logmuse>=0.2.5
Requires-Dist: pyyaml
Requires-Dist: ubiquerg>=0.8.0
Requires-Dist: yacman>=0.9.3
Requires-Dist: pandas
Requires-Dist: eido
Requires-Dist: jinja2
Provides-Extra: dbbackend
Requires-Dist: psycopg>=3.1.13; extra == "dbbackend"
Requires-Dist: pydantic<3.0.0,>=2.5.3; extra == "dbbackend"
Requires-Dist: sqlmodel>=0.0.14; extra == "dbbackend"
Provides-Extra: pipestatreader
Requires-Dist: fastapi; extra == "pipestatreader"
Requires-Dist: uvicorn; extra == "pipestatreader"
Dynamic: author
Dynamic: classifier
Dynamic: description
Dynamic: description-content-type
Dynamic: home-page
Dynamic: keywords
Dynamic: license
Dynamic: provides-extra
Dynamic: requires-dist
Dynamic: summary
